Workbook

Sheet Overview
I4: Denis To-do:
I5: 1. Make the Timeline
I6: 2. dinner stuffffz
I7: 3. Food Brainstorming
I10: Coststststst
I13: Sunday | J13: 45718
C14: Team Bonding Time!!!
C15: Let's get to know one another some more!!!
C16: It'll be fun, starting off with dinner at Ehwa's Restaurant, then straight to Karaoke(?) | I16: Jess To-do:
I17: - check in w/ Justin about revised plan (Ehwa J Bar, board game cafe)
C18: Timeline Summary | I18: - contact activity space
C19: 45735
C20: DINNER: 6-7:30 PM
C21: Activity: 8-10 PM | I21: Date range 16-23 preferably Sunday
I23: Sunday 16 / Sunday 23

Sheet Timeline (Main Plan)
A1: Time | B1: Activity | C1: Details | D1: Notes
A2: 0.33333333 | B2: Commute → SLC (If meeting up) or Ehwa J Restaurant & Bar (if Commuting directly) | C2: Commute costs and times based on Individual's circumstances. | D2: If you haven't already, try: https://www.gotransit.com/en/student-savings
A3: 0.375
A4: 0.41666667
A5: 0.45833333
A6: 0.5
A7: 0.54166667
A8: 0.58333333
A9: 0.625
A10: 0.66666667
A11: 0.70833333 | B11: Meet @ SLC | C11: Meetup & Commute together! | D11: Those who cannot meetup can go to the restaurant directly and follow the main timeline!
A12: 0.73611111 | B12: Commute → Ehwa J Restaurant & Bar
A13: 0.75 | B13: Dine-in @ Ehwa J Restaurant & Bar | D13: Menu: https://ehwa.ca/downtown-menu/
A14: 0.79166667
A15: 0.8125 | B15: Commute → Bar Plus Karaoke
A16: 0.83333333 | B16: Activity @ Bar Plus Karaoke | C16: ~$6-11pp | D16: call for group of <16, fill out form for group >16 https://bar-plus.com/
A17: 0.875
A18: 0.91666667 | B18: Home time!!! | C18: Closest TTC Stations: 1. Bloor-Yonge (2min walk) 2. Bay (6min walk) 3. Wellesley (6min walk)
A19: 0.95833333
A20: 0
A21: 0.041666667
A22: 0.083333333

Sheet Commute times
B1: Restaurant | C1: Activity | D1: Commute
A2: Main plan: | B2: Ehwa J Bar | C2: Twilight Cafe (Yonge) | D2: Ehwa → Twilight: 3min walk (190m)
A3: Backup: | B3: Pai Thai Toronto | C3: Bar+ Karaoke | D3: Pai → Bar+: 25min walk OR 17min TTC (1.7km)
A4: Backup 2: | B4: Ehwa J Bar | C4: Bar+ Karaoke | D4: Ehwa J Bar → Bar+: 15min walk OR 8min TTC (1.1km)
A5: Backup 3: | B5: Pai Thai Toronto | C5: Twilight Cafe (Yonge) | D5: Pai → Twilight: 21min TTC (2.9km)
A6: Backup 4: | B6: Ehwa J Bar | C6: VIP Billiards & Lounge | D6: Ehwa J Bar →VIP Billiards & Lounge: 26-33min TTC (4 km)
A7: Backup 5: | B7: Pai Thai Toronto | C7: VIP Billiards & Lounge | D7: Ehwa J Bar →VIP Billiards & Lounge: 26-33min TTC (4 km)

Sheet Activities
A1: Activity | B1: Description | C1: Cost Per Person | D1: Avg. Time | E1: Pros | F1: Cons | G1: Priority | H1: Notes
A2: Mafia | C2: - | D2: 30-90 Minutes | E2: - Everyone can be involved | F2: - Idk how to play (at someone's place) | G2: 0 | I2: scrapped
A3: REC ROOM | B3: Location: 255 Bremner Blvd, Toronto, ON M5V 3L9 Website: https://www.therecroom.com/toronto-roundhouse | C3: - | D3: - | E3: - Everyone can be involved | F3: - Toronto REC Room apparently does not have bowling. | G3: 1 | I3: scrapped
A4: Twilight Cafe | B4: Location: 667 Yonge St, Toronto, ON M4Y 1Z9 Website: https://www.twilightcafe.ca/ | C4: ~$6pp | D4: 1-2 hours | E4: - Everyone can be involved, cheap, variety of games, spacious, food and drinks, affordable | F4: - small tables, split up groups | G4: 5 | H4: - call for group of <16, fill out form for group >16 | I4: best option
A5: Bar+ Karaoke | B5: Location: 360 Yonge St, Toronto, ON M5B 1S5 (https://bar-plus.com/) | C5: ~$6pp-11pp (depending on group size) | D5: 1-2 hours | E5: - private rooms (small/large, depending on group size), short commute, affordable | F5: - engagement might be difficult for some people | G5: 3 | H5: submit form on website for group size/event details | I5: considering
A6: Ballroom bowl | B6: Location: 1 Bloor St E Unit CRU6, Toronto, ON M4W 0A8 (https://yorkville.theballroombowl.ca/bowling) | C6: ~$31-37pp (depending on group size) | D6: 1-2 hours | E6: - private rooms, group engagement | F6: - high-end/expensive | G6: 1 | H6: submit form on website for group size/event details | I6: pricy af
A7: VIP Billiards & Lounge | B7: Location: 842 College St, Toronto, ON M6H 1A2 (https://vipbilliardsclub.com/) | C7: ~$5-10pp (depending on group size) | D7: 1-2 hours | E7: - relaxed activity, affordable | F7: - small tables, split up groups, limited involvement | G7: 3 | H7: call | I7: considering

Sheet Foods
A1: Restaurant | B1: Description | C1: Estimated Cost Per Person (May be Inaccurate) | D1: Pros | E1: Cons | F1: Delivery | G1: Dine-In | H1: Cuisine Origin | I1: Priority
A2: Ehwa Bar & Restaurant | B2: Hours of Operation on Sunday: 5 PM - 3 AM Address: 16 Isabella St, Toronto, ON M4Y 2A1; Contact: +14169289990 Menu: https://www.instagram.com/ehwa_restaurant/ Wbsite: https://ehwa.ca/downtown-menu/ | C2: $20-$30 | D2: - yummy - has dine-in with space - super close to karaoke and bowling and boardgame cafeeeee | E2: - | F2: Yes | G2: Yes | H2: Korean | I2: 5
A3: PAI Thai Northern Thai Kitchen | B3: Hours of Operation on Sunday: 11:45 AM - 9:30 PM Address: 18 Duncan St Downtown, Ontario M5H 3G8 Contact: +1 (416) 901-4724 Website: https://www.paitoronto.com/ Reserve: https://www.opentable.ca/restref/client/?restref=231088&lang=en-CA&corrid=0424c798-2474-4280-8a7e-321d7e37c5d5 | C3: $20-$30 | E3: - | F3: Yes | G3: Yes | H3: Thailand | I3: 5
A4: Haidilao Hot Pot Toronto Downtown | B4: Hours of Operation on Sunday: 11:00 AM - 3:00 AM Address: 237 Yonge St, Toronto, ON M5B 1N8 Contact: +14377781068 Website: https://www.haidilao-inc.com/ca | C4: $10-$20 | D4: - Hotpot - Hours of Operation bodes well for the timeline | E4: - Little bit far. | F4: Yes | G4: Yes | H4: Chinese | I4: 3
A5: Gyu-Kaku Japanese BBQ | B5: Hours of Operation on Sunday: 11:30 AM - 8:30 PM Address: 81 Church St, Toronto, ON M5C 2G2 Contact: +16473512378 Website: http://www.gyu-kaku.com/toronto | C5: $10-$20 | D5: - Sushi - Hours of Operation bodes well for the timeline | E5: - Little bit far. | F5: Yes | G5: Yes | H5: Japanese | I5: 2
A6: Mom's Pan-Fried Bun | B6: Hours of Operation on Sunday: 10 AM - 10 PM Address: 185 Dundas St W, Toronto, ON M5G 1C7 Contact: +16473468368 Website: https://momspanfriedbun.com/ Menu: https://momspanfriedbun.com/ | C6: $10-$20 | D6: - Midsize Menu - Dumplings, Noodles and moreee | E6: - Little bit far. | F6: Yes | G6: Yes | H6: Chinese | I6: 2
A7: Happy Lamb Hot Pot, Toronto | B7: Hours of Operation on Sunday: 11:30 AM - 10:30 AM Address: 421 Dundas St W, Toronto, ON M5T 2W4 Contact: +14167928885 Website: https://happylambhotpotca.com/ | C7: $30-$40 | D7: - Hotpot - Hours of Operation bodes well for the timeline | E7: - Little bit far. | F7: Yes | G7: Yes | H7: Mongolian | I7: 2
A8: H-Mart | B8: Hours of Operation on Sunday: 9 AM - 11 PM Address: 338 Yonge St, Toronto, ON M5B 1R8 Contact: +16473503100 BBQ Menu: https://www.hmartca.com/bbq | C8: $10-$15 | D8: - Menu is plentiful. - Nearby - Familiar - Just cost effective - Hours of Operation bodes well for the timeline. | E8: - | F8: Yes | G8: No | H8: Korean | I8: 2
A9: Banh Mi Boys | B9: Hours of Operation on Sunday: 11 AM - 8 PM Address: 329 Yonge St, Toronto, ON M5B 1R7 Contact: +14169770303 Website: https://banhmiboys.com/ Menu: https://banhmiboys.order-online.ai/#/ | C9: $10-$20 | D9: - Banh Mi - Nearby - Familiar Cuisine - Hours of Operation bodes well for the timeline. | E9: - Expensive for just Banh Mi - Too small to dine in | F9: Yes | G9: Yes | H9: Vietnamese | I9: 2
A10: B-Town pizza | B10: Hours of Operation on Sunday: 11 AM - 2 AM Address: 13 Elm St, Toronto, ON M5G 1H1 Contact: +14168130525 Website: https://btownpizza.ca/ | C10: $10-$30 | D10: - Feeds lots - Nearby - Familiar - Hours of Operation bodes well for the timeline. | F10: Yes | G10: Yes | H10: Italian | I10: 2
A11: Bapbo Korean Restaurant | B11: Hours of Operation on Sunday: 11:30 AM - 10 PM Address: 142 Dundas St W, Toronto, ON M5G 1C3 Contact: +16473523312 Website: https://www.bapbo.com/menus | C11: $20-$30 | D11: - Menu is plentiful. - Portions are plentiful - Familiar - Hours of Operation bodes well for the timeline. | E11: - Expensive | F11: Yes | G11: Yes | H11: Korean | I11: 2
A12: Daldongnae Korean BBQ - Dundas Square | B12: Hours of Operation on Sunday: 11:30 AM - 1 AM Address: 361 Yonge St Second Floor, Toronto, ON M5B 1S1 Contact: +16473688470 Website: https://www.daldongnaebbq.com/ | C12: $20-$40 | D12: - Menu is plentiful. - Nearby - Familiar - Hours of Operation bodes well for the timeline. | E12: - Expensive | F12: No | G12: Yes | H12: Korean | I12: 2
A13: Pho Ha Noi | B13: Hours of Operation on Sunday: 4 PM - 4 AM Address: 374 College St, Toronto, ON M5T 1S6 Contact: +14169224415 Website: N/A Menu: N/A | C13: $10-$20 | D13: - Pho - Nearby - Familiar Cuisine - Hours of Operation bodes well for the timeline. | F13: Yes | G13: Yes | H13: Vietnamese | I13: 1
A14: Pho Pasteur Restaurant | B14: Hours of Operation on Sunday: 4 PM - 4 AM Address: 525 Dundas St W, Toronto, ON M5T 1H3 Contact: +14169224415 Website: http://phopasteur.ca/ Menu: http://phopasteur.ca/#menu | C14: $20-$30 | D14: - Pho - Nearby - Familiar Cuisine - Hours of Operation bodes well for the timeline. | F14: Yes | G14: Yes | H14: Vietnamese | I14: 1
A15: Pho Anh Vu | B15: Hours of Operation on Sunday: 11:30 AM - 10:30 AM Address: 421 Dundas St W, Toronto, ON M5T 2W4 Contact: +14167928885 Website: N/A | C15: $20-$30 | D15: - Pho - Nearby - Familiar Cuisine - Hours of Operation bodes well for the timeline. | F15: Yes | G15: Yes | H15: Vietnamese | I15: 1

Sheet Order Summary
C1: If you're trying to see who ordered what, see the PivotTable sheet!!! | F1: Salad
A2: Order Item | B2: Cost | C2: Quantity | D2: Total Cost (After Tax) | F2: Pasta | H2: Name | I2: Allergies | J2: Other Messages
A3: Bocconcini Salad | B3: 12.99 | C3: =SUM('Order List PivotTable'!C:C) -> 0 | D3: =1.13*(C3*B3) -> 0 | F3: Tonkatsu | H3: ='Order List Table'!C2 -> Alex | I3: ='Order List Table'!E2 | J3: ='Order List Table'!AG2
A4: Ehwa Mini Salad | B4: 7.99 | C4: =SUM('Order List PivotTable'!D:D) -> 1 | D4: =1.13*(C4*B4) -> 9.0287 | F4: Hamburg Steak | H4: ='Order List Table'!C3 -> Denis | I4: ='Order List Table'!E3 -> NO I EAT EVERYTHING!!! | J4: ='Order List Table'!AG3 -> This is just test submission for the sheets!!!
A5: Caesar Salad | B5: 7.99 | C5: =SUM('Order List PivotTable'!E:E) -> 0 | D5: =1.13*(C5*B5) -> 0 | F5: Hansang | H5: ='Order List Table'!C4 -> Trang | I5: ='Order List Table'!E4 -> nuts allergies | J5: ='Order List Table'!AG4 -> draft but also my real response 😊 love u guys
A6: Ttukbaegi Pasta | B6: 23.99 | C6: =SUM('Order List PivotTable'!F:F) -> 0 | D6: =1.13*(C6*B6) -> 0 | F6: Omurice | H6: ='Order List Table'!C5 -> Khanh | I6: ='Order List Table'!E5 | J6: ='Order List Table'!AG5
A7: Ehwa Clam Pasta | B7: 20.99 | C7: =SUM('Order List PivotTable'!G:G) -> 0 | D7: =1.13*(C7*B7) -> 0 | F7: Main | H7: ='Order List Table'!C6 -> Ivy | I7: ='Order List Table'!E6 -> Nope | J7: ='Order List Table'!AG6 -> yum yum yum yum yum yum💔
A8: Pork Belly Chilli Cream Pasta | B8: 20.99 | C8: =SUM('Order List PivotTable'!H:H) -> 1 | D8: =1.13*(C8*B8) -> 23.7187 | F8: Pizza | H8: ='Order List Table'!C7 -> Britney | I8: ='Order List Table'!E7 -> no | J8: ='Order List Table'!AG7 -> no
A9: Polack Roe Pasta | B9: 20.99 | C9: =SUM('Order List PivotTable'!I:I) -> 0 | D9: =1.13*(C9*B9) -> 0 | F9: Korean Lunch Box | H9: ='Order List Table'!C8 -> Teresa | I9: ='Order List Table'!E8 -> No | J9: ='Order List Table'!AG8
A10: Ehwa Tonkatsu | B10: 18.99 | C10: =SUM('Order List PivotTable'!J:J) -> 2 | D10: =1.13*(C10*B10) -> 42.9174 | H10: ='Order List Table'!C9 -> Kathy | I10: ='Order List Table'!E9 -> No allergies!! | J10: ='Order List Table'!AG9 -> No
A11: Cheese Tonkatsu | B11: 21.99 | C11: =SUM('Order List PivotTable'!K:K) -> 0 | D11: =1.13*(C11*B11) -> 0 | H11: ='Order List Table'!C10 -> Presly | I11: ='Order List Table'!E10 -> No | J11: ='Order List Table'!AG10 -> I’m not writing anything again
A12: Spicy Cream Tonkatsu | B12: 22.99 | C12: =SUM('Order List PivotTable'!L:L) -> 0 | D12: =1.13*(C12*B12) -> 0 | H12: ='Order List Table'!C11 -> Bao | I12: ='Order List Table'!E11 -> dị ứng với người không iu mình 🥰 | J12: ='Order List Table'!AG11 -> dạ hôm đó mình nhậu nhẹt uống tí cồn được không ạ 🥰🤟🏻
A13: Fish Katsu | B13: 22.99 | C13: =SUM('Order List PivotTable'!M:M) -> 0 | D13: =1.13*(C13*B13) -> 0 | H13: ='Order List Table'!C12 -> Khuong Hoang | I13: ='Order List Table'!E12 -> ko | J13: ='Order List Table'!AG12 -> quynh lon
A14: Ehwa Hamburg Steak | B14: 21.99 | C14: =SUM('Order List PivotTable'!N:N) -> 1 | D14: =1.13*(C14*B14) -> 24.8487 | H14: ='Order List Table'!C14 | I14: ='Order List Table'!E14 | J14: ='Order List Table'!J13
A15: Chilli Cream Hamburg Steak | B15: 21.99 | C15: =SUM('Order List PivotTable'!O:O) -> 0 | D15: =1.13*(C15*B15) -> 0 | H15: ='Order List Table'!C15 | I15: ='Order List Table'!E15 | J15: ='Order List Table'!AG15
A16: Ehwa Jeong-Sik | B16: 24.99 | C16: =SUM('Order List PivotTable'!P:P) -> 0 | D16: =1.13*(C16*B16) -> 0 | H16: ='Order List Table'!C17 | I16: ='Order List Table'!E17 | J16: ='Order List Table'!AG17
A17: Spicy Pork | B17: 19.99 | C17: =SUM('Order List PivotTable'!Q:Q) -> 0 | D17: =1.13*(C17*B17) -> 0 | H17: ='Order List Table'!C18 | I17: ='Order List Table'!E18 | J17: ='Order List Table'!AG18
A18: Pork Belly | B18: 19.99 | C18: =SUM('Order List PivotTable'!R:R) -> 0 | D18: =1.13*(C18*B18) -> 0 | H18: ='Order List Table'!C19 | I18: ='Order List Table'!E19 | J18: ='Order List Table'!AG19
A19: Bulgogi | B19: 19.99 | C19: =SUM('Order List PivotTable'!S:S) -> 1 | D19: =1.13*(C19*B19) -> 22.5887 | H19: ='Order List Table'!C20 | I19: ='Order List Table'!E20 | J19: ='Order List Table'!AG20
A20: Original Omurice | B20: 17.99 | C20: =SUM('Order List PivotTable'!T:T) -> 0 | D20: =1.13*(C20*B20) -> 0 | H20: ='Order List Table'!C21 | I20: ='Order List Table'!E21 | J20: ='Order List Table'!AG21
A21: Humburg Steak Omurice | B21: 22.99 | C21: =SUM('Order List PivotTable'!U:U) -> 1 | D21: =1.13*(C21*B21) -> 25.9787 | H21: ='Order List Table'!C22 | I21: ='Order List Table'!E22 | J21: ='Order List Table'!AG22
A22: Tonkatsu Omurice | B22: 20.99 | C22: =SUM('Order List PivotTable'!V:V) -> 1 | D22: =1.13*(C22*B22) -> 23.7187 | H22: ='Order List Table'!C23 | I22: ='Order List Table'!E23 | J22: ='Order List Table'!AG23
A23: Sausage Omurice | B23: 19.99 | C23: =SUM('Order List PivotTable'!W:W) -> 1 | D23: =1.13*(C23*B23) -> 22.5887 | H23: ='Order List Table'!C24 | I23: ='Order List Table'!E24 | J23: ='Order List Table'!AG24
A24: Army Soup | B24: 19.99 | C24: =SUM('Order List PivotTable'!X:X) -> 2 | D24: =1.13*(C24*B24) -> 45.1774 | H24: ='Order List Table'!C25 | I24: ='Order List Table'!E25 | J24: ='Order List Table'!AG25
A25: Soon Tofu Soup | B25: 19.99 | C25: =SUM('Order List PivotTable'!Y:Y) -> 0 | D25: =1.13*(C25*B25) -> 0 | H25: ='Order List Table'!C26 | I25: ='Order List Table'!E26 | J25: ='Order List Table'!AG26
A26: Braised Spicy Pork Rib | B26: 23.99 | C26: =SUM('Order List PivotTable'!Z:Z) -> 0 | D26: =1.13*(C26*B26) -> 0 | H26: ='Order List Table'!C27 | I26: ='Order List Table'!E27 | J26: ='Order List Table'!AG27
A27: Yukhoe Bibimbap | B27: 18.99 | C27: =SUM('Order List PivotTable'!AA:AA) -> 3 | D27: =1.13*(C27*B27) -> 64.3761 | H27: ='Order List Table'!C28 | I27: ='Order List Table'!E28 | J27: ='Order List Table'!AG28
A28: Injeolmi Honey Pizza | B28: 16.99 | C28: =SUM('Order List PivotTable'!AB:AB) -> 0 | D28: =1.13*(C28*B28) -> 0 | H28: ='Order List Table'!C29 | I28: ='Order List Table'!E29 | J28: ='Order List Table'!AG29
A29: Korean Lunch Box | B29: 19.99 | C29: =SUM('Order List PivotTable'!AC:AC) -> 0 | D29: =1.13*(C29*B29) -> 0 | H29: ='Order List Table'!C30 | I29: ='Order List Table'!E30 | J29: ='Order List Table'!AG30
A30: Grand Totals | B30: =SUM(B3:B29) -> 533.73 | C30: =SUM(C3:C29) -> 14 | D30: =SUM(D3:D29) -> 304.9418 | H30: ='Order List Table'!C31 | I30: ='Order List Table'!E31 | J30: ='Order List Table'!AG31
H31: ='Order List Table'!C32 | I31: ='Order List Table'!E32 | J31: ='Order List Table'!AG32
H32: ='Order List Table'!C33 | I32: ='Order List Table'!E33 | J32: ='Order List Table'!AG33
H33: ='Order List Table'!C34 | I33: ='Order List Table'!E34 | J33: ='Order List Table'!AG34
H34: ='Order List Table'!C35 | I34: ='Order List Table'!E35 | J34: ='Order List Table'!AG35
H35: ='Order List Table'!C36 | I35: ='Order List Table'!E36 | J35: ='Order List Table'!AG36

Sheet Sheet13

Sheet Order List PivotTable
AD1: Individual Cost (Before Tax) | AE1: Individual Cost (After Tax) | AF1: Total Cost W/ Karaoke
AD2: =(C2*12.99)+(D2*7.99)+(E2*7.99)+(F2*23.99)+(G2*20.99)+(H2*20.99)+(I2*20.99)+(J2*18.99)+(K2*21.99)+(L2*22.99)+(M2*22.99)+(N2*21.99)+(O2*21.99)+(P2*21.99)+(Q2*19.99)+(R2*19.99)+(S2*19.99)+(T2*17.99)+(U2*22.99)+(V2*20.99)+(W2*19.99)+(X2*19.99)+(Y2*19.99)+(Z2*23.99)+(AA2*18.99)+(AB2*16.99)+(AC2*19.99) -> 18.99 | AE2: =AD2*1.13 -> 21.4587 | AF2: =AE2+11.99 -> 33.4487
AD3: =(C3*12.99)+(D3*7.99)+(E3*7.99)+(F3*23.99)+(G3*20.99)+(H3*20.99)+(I3*20.99)+(J3*18.99)+(K3*21.99)+(L3*22.99)+(M3*22.99)+(N3*21.99)+(O3*21.99)+(P3*21.99)+(Q3*19.99)+(R3*19.99)+(S3*19.99)+(T3*17.99)+(U3*22.99)+(V3*20.99)+(W3*19.99)+(X3*19.99)+(Y3*19.99)+(Z3*23.99)+(AA3*18.99)+(AB3*16.99)+(AC3*19.99) -> 70.96 | AE3: =AD3*1.13 -> 80.1848 | AF3: =AE3+11.99 -> 92.1748
AD4: =(C4*12.99)+(D4*7.99)+(E4*7.99)+(F4*23.99)+(G4*20.99)+(H4*20.99)+(I4*20.99)+(J4*18.99)+(K4*21.99)+(L4*22.99)+(M4*22.99)+(N4*21.99)+(O4*21.99)+(P4*21.99)+(Q4*19.99)+(R4*19.99)+(S4*19.99)+(T4*17.99)+(U4*22.99)+(V4*20.99)+(W4*19.99)+(X4*19.99)+(Y4*19.99)+(Z4*23.99)+(AA4*18.99)+(AB4*16.99)+(AC4*19.99) -> 20.99 | AE4: =AD4*1.13 -> 23.7187 | AF4: =AE4+11.99 -> 35.7087
AD5: =(C5*12.99)+(D5*7.99)+(E5*7.99)+(F5*23.99)+(G5*20.99)+(H5*20.99)+(I5*20.99)+(J5*18.99)+(K5*21.99)+(L5*22.99)+(M5*22.99)+(N5*21.99)+(O5*21.99)+(P5*21.99)+(Q5*19.99)+(R5*19.99)+(S5*19.99)+(T5*17.99)+(U5*22.99)+(V5*20.99)+(W5*19.99)+(X5*19.99)+(Y5*19.99)+(Z5*23.99)+(AA5*18.99)+(AB5*16.99)+(AC5*19.99) -> 19.99 | AE5: =AD5*1.13 -> 22.5887 | AF5: =AE5+11.99 -> 34.5787
AD6: =(C6*12.99)+(D6*7.99)+(E6*7.99)+(F6*23.99)+(G6*20.99)+(H6*20.99)+(I6*20.99)+(J6*18.99)+(K6*21.99)+(L6*22.99)+(M6*22.99)+(N6*21.99)+(O6*21.99)+(P6*21.99)+(Q6*19.99)+(R6*19.99)+(S6*19.99)+(T6*17.99)+(U6*22.99)+(V6*20.99)+(W6*19.99)+(X6*19.99)+(Y6*19.99)+(Z6*23.99)+(AA6*18.99)+(AB6*16.99)+(AC6*19.99) -> 18.99 | AE6: =AD6*1.13 -> 21.4587 | AF6: =AE6+11.99 -> 33.4487
AD7: =(C7*12.99)+(D7*7.99)+(E7*7.99)+(F7*23.99)+(G7*20.99)+(H7*20.99)+(I7*20.99)+(J7*18.99)+(K7*21.99)+(L7*22.99)+(M7*22.99)+(N7*21.99)+(O7*21.99)+(P7*21.99)+(Q7*19.99)+(R7*19.99)+(S7*19.99)+(T7*17.99)+(U7*22.99)+(V7*20.99)+(W7*19.99)+(X7*19.99)+(Y7*19.99)+(Z7*23.99)+(AA7*18.99)+(AB7*16.99)+(AC7*19.99) -> 18.99 | AE7: =AD7*1.13 -> 21.4587 | AF7: =AE7+11.99 -> 33.4487
AD8: =(C8*12.99)+(D8*7.99)+(E8*7.99)+(F8*23.99)+(G8*20.99)+(H8*20.99)+(I8*20.99)+(J8*18.99)+(K8*21.99)+(L8*22.99)+(M8*22.99)+(N8*21.99)+(O8*21.99)+(P8*21.99)+(Q8*19.99)+(R8*19.99)+(S8*19.99)+(T8*17.99)+(U8*22.99)+(V8*20.99)+(W8*19.99)+(X8*19.99)+(Y8*19.99)+(Z8*23.99)+(AA8*18.99)+(AB8*16.99)+(AC8*19.99) -> 18.99 | AE8: =AD8*1.13 -> 21.4587 | AF8: =AE8+11.99 -> 33.4487
AD9: =(C9*12.99)+(D9*7.99)+(E9*7.99)+(F9*23.99)+(G9*20.99)+(H9*20.99)+(I9*20.99)+(J9*18.99)+(K9*21.99)+(L9*22.99)+(M9*22.99)+(N9*21.99)+(O9*21.99)+(P9*21.99)+(Q9*19.99)+(R9*19.99)+(S9*19.99)+(T9*17.99)+(U9*22.99)+(V9*20.99)+(W9*19.99)+(X9*19.99)+(Y9*19.99)+(Z9*23.99)+(AA9*18.99)+(AB9*16.99)+(AC9*19.99) -> 21.99 | AE9: =AD9*1.13 -> 24.8487 | AF9: =AE9+11.99 -> 36.8387
AD10: =(C10*12.99)+(D10*7.99)+(E10*7.99)+(F10*23.99)+(G10*20.99)+(H10*20.99)+(I10*20.99)+(J10*18.99)+(K10*21.99)+(L10*22.99)+(M10*22.99)+(N10*21.99)+(O10*21.99)+(P10*21.99)+(Q10*19.99)+(R10*19.99)+(S10*19.99)+(T10*17.99)+(U10*22.99)+(V10*20.99)+(W10*19.99)+(X10*19.99)+(Y10*19.99)+(Z10*23.99)+(AA10*18.99)+(AB10*16.99)+(AC10*19.99) -> 19.99 | AE10: =AD10*1.13 -> 22.5887 | AF10: =AE10+11.99 -> 34.5787
AD11: =(C11*12.99)+(D11*7.99)+(E11*7.99)+(F11*23.99)+(G11*20.99)+(H11*20.99)+(I11*20.99)+(J11*18.99)+(K11*21.99)+(L11*22.99)+(M11*22.99)+(N11*21.99)+(O11*21.99)+(P11*21.99)+(Q11*19.99)+(R11*19.99)+(S11*19.99)+(T11*17.99)+(U11*22.99)+(V11*20.99)+(W11*19.99)+(X11*19.99)+(Y11*19.99)+(Z11*23.99)+(AA11*18.99)+(AB11*16.99)+(AC11*19.99) -> 19.99 | AE11: =AD11*1.13 -> 22.5887 | AF11: =AE11+11.99 -> 34.5787
AD12: =(C12*12.99)+(D12*7.99)+(E12*7.99)+(F12*23.99)+(G12*20.99)+(H12*20.99)+(I12*20.99)+(J12*18.99)+(K12*21.99)+(L12*22.99)+(M12*22.99)+(N12*21.99)+(O12*21.99)+(P12*21.99)+(Q12*19.99)+(R12*19.99)+(S12*19.99)+(T12*17.99)+(U12*22.99)+(V12*20.99)+(W12*19.99)+(X12*19.99)+(Y12*19.99)+(Z12*23.99)+(AA12*18.99)+(AB12*16.99)+(AC12*19.99) -> 19.99 | AE12: =AD12*1.13 -> 22.5887 | AF12: =AE12+11.99 -> 34.5787
AD13: =(C13*12.99)+(D13*7.99)+(E13*7.99)+(F13*23.99)+(G13*20.99)+(H13*20.99)+(I13*20.99)+(J13*18.99)+(K13*21.99)+(L13*22.99)+(M13*22.99)+(N13*21.99)+(O13*21.99)+(P13*21.99)+(Q13*19.99)+(R13*19.99)+(S13*19.99)+(T13*17.99)+(U13*22.99)+(V13*20.99)+(W13*19.99)+(X13*19.99)+(Y13*19.99)+(Z13*23.99)+(AA13*18.99)+(AB13*16.99)+(AC13*19.99) -> 0 | AE13: =AD13*1.13 -> 0 | AF13: =AE13+11.99 -> 11.99
... AD22: =(C22*12.99)+(D22*7.99)+(E22*7.99)+(F22*23.99)+(G22*20.99)+(H22*20.99)+(I22*20.99)+(J22*18.99)+(K22*21.99)+(L22*22.99)+(M22*22.99)+(N22*21.99)+(O22*21.99)+(P22*21.99)+(Q22*19.99)+(R22*19.99)+(S22*19.99)+(T22*17.99)+(U22*22.99)+(V22*20.99)+(W22*19.99)+(X22*19.99)+(Y22*19.99)+(Z22*23.99)+(AA22*18.99)+(AB22*16.99)+(AC22*19.99) -> 0 | AE22: =AD22*1.13 -> 0 | AF22: =AE22+11.99 -> 11.99

Sheet Order List Table
A1: Timestamp | B1: Email address | C1: First Name: | D1: Last Name: | E1: Is there anything we should know about? (i.e. allergies) Mình có lưu ý gì đặc biệt hong? (dị ứng,...) | F1: Caesar Salad | $7.99 | G1: Bocconcini Salad | $12.99 | H1: Ehwa Mini Salad | $7.99 | I1: Ttukbaegi Pasta | $23.99 | J1: Ehwa Clam Pasta | $20.99 | K1: Pork Belly Chilli Cream Pasta | $20.99 | L1: Polack Roe Pasta | $20.99 | M1: Ehwa Tonkatsu | $18.99 | N1: Cheese Tonkatsu | $21.99 | O1: Spicy Cream Tonkatsu | $22.99 | P1: Fish Katsu | $22.99 | Q1: Ehwa Hamburg Steak | $21.99 | R1: Chilli Cream Hamburg Steak | $21.99 | S1: Ehwa Jeong-Sik | $24.99 | T1: Spicy Pork | $19.99 | U1: Pork Belly | $19.99 | V1: Bulgogi | $19.99 | W1: Original | $17.99 | X1: Humburg Steak | $22.99 | Y1: Tonkatsu | $20.99 | Z1: Sausage | $19.99 | AA1: Army Soup | $19.99 | AB1: Soon Tofu Soup | $19.99 | AC1: Braised Spicy Pork Rib | $23.99 | AD1: Yukhoe Bibimbap | $18.99 | AE1: Injeolmi Honey Pizza | $16.99 | AF1: Lunch Box | $xx.xx | AG1: Is there anything you want to tell us? Nhà mình có tâm sự gì hong nè 😊
A2: 45733.517 | B2: alex.kieu@torontomu.ca | C2: Alex | D2: Kieu | V2: Order
A3: 45733.844 | B3: denis.thai@torontomu.ca | C3: Denis | D3: Thai | E3: NO I EAT EVERYTHING!!! | AA3: Order | AG3: This is just test submission for the sheets!!!
A4: 45733.939 | B4: huyentrang.pham@torontomu.ca | C4: Trang | D4: Pham | E4: nuts allergies | AA4: Order | AG4: draft but also my real response 😊 love u guys
A5: 45734.658 | B5: khanh.su@torontomu.ca | C5: Khanh | D5: Su | Q5: Order
A6: 45734.661 | B6: my.vu@torontomu.ca | C6: Ivy | D6: Vu | E6: Nope | M6: Order | AG6: yum yum yum yum yum yum💔
A7: 45734.673 | B7: britney.phung@torontomu.ca | C7: Britney | D7: Phung | E7: no | M7: Order | AG7: no
A8: 45734.679 | B8: teresa.van@torontomu.ca | C8: Teresa | D8: Van | E8: No | AD8: Order
A9: 45734.683 | B9: k1bui@torontomu.ca | C9: Kathy | D9: Bui | E9: No allergies!! | Z9: Order | AG9: No
A10: 45734.796 | B10: presly.trinh@torontomu.ca | C10: Presly | D10: Trinh | E10: No | Y10: Order | AG10: I’m not writing anything again
A11: 45734.911 | B11: ngocthienbao.le@torontomu.ca | C11: Bao | D11: Le | E11: dị ứng với người không iu mình 🥰 | H11: Order | K11: Order | X11: Order | AD11: Order | AG11: dạ hôm đó mình nhậu nhẹt uống tí cồn được không ạ 🥰🤟🏻
A12: 45735.047 | B12: Khuonghoang.tran@torontomu.ca | C12: Khuong Hoang | D12: Tran | E12: ko | AD12: Order | AG12: quynh lon

Sheet Detail6-Trang-Pham
A1: Timestamp | B1: Email address | C1: First Name: | D1: Last Name: | E1: Is there anything we should know about? (i.e. allergies) Mình có lưu ý gì đặc biệt hong? (dị ứng,...) | F1: Caesar Salad | $7.99 | G1: Bocconcini Salad | $12.99 | H1: Ehwa Mini Salad | $7.99 | I1: Ttukbaegi Pasta | $23.99 | J1: Ehwa Clam Pasta | $20.99 | K1: Pork Belly Chilli Cream Pasta | $20.99 | L1: Polack Roe Pasta | $20.99 | M1: Ehwa Tonkatsu | $18.99 | N1: Cheese Tonkatsu | $21.99 | O1: Spicy Cream Tonkatsu | $22.99 | P1: Fish Katsu | $22.99 | Q1: Ehwa Hamburg Steak | $21.99 | R1: Chilli Cream Hamburg Steak | $21.99 | S1: Ehwa Jeong-Sik | $24.99 | T1: Spicy Pork | $19.99 | U1: Pork Belly | $19.99 | V1: Bulgogi | $19.99 | W1: Original | $17.99 | X1: Humburg Steak | $22.99 | Y1: Tonkatsu | $20.99 | Z1: Sausage | $19.99 | AA1: Army Soup | $19.99 | AB1: Soon Tofu Soup | $19.99 | AC1: Braised Spicy Pork Rib | $23.99 | AD1: Yukhoe Bibimbap | $18.99 | AE1: Injeolmi Honey Pizza | $16.99 | AF1: Lunch Box | $xx.xx | AG1: Is there anything you want to tell us? Nhà mình có tâm sự gì hong nè 😊
A2: 45733.939 | B2: huyentrang.pham@torontomu.ca | C2: Trang | D2: Pham | E2: nuts allergies | AA2: Order | AG2: draft but also my real response 😊 love u guys

Sheet Detail5-Trang-Pham
A1: Timestamp | B1: Email address | C1: First Name: | D1: Last Name: | E1: Is there anything we should know about? (i.e. allergies) Mình có lưu ý gì đặc biệt hong? (dị ứng,...) | F1: Caesar Salad | $7.99 | G1: Bocconcini Salad | $12.99 | H1: Ehwa Mini Salad | $7.99 | I1: Ttukbaegi Pasta | $23.99 | J1: Ehwa Clam Pasta | $20.99 | K1: Pork Belly Chilli Cream Pasta | $20.99 | L1: Polack Roe Pasta | $20.99 | M1: Ehwa Tonkatsu | $18.99 | N1: Cheese Tonkatsu | $21.99 | O1: Spicy Cream Tonkatsu | $22.99 | P1: Fish Katsu | $22.99 | Q1: Ehwa Hamburg Steak | $21.99 | R1: Chilli Cream Hamburg Steak | $21.99 | S1: Ehwa Jeong-Sik | $24.99 | T1: Spicy Pork | $19.99 | U1: Pork Belly | $19.99 | V1: Bulgogi | $19.99 | W1: Original | $17.99 | X1: Humburg Steak | $22.99 | Y1: Tonkatsu | $20.99 | Z1: Sausage | $19.99 | AA1: Army Soup | $19.99 | AB1: Soon Tofu Soup | $19.99 | AC1: Braised Spicy Pork Rib | $23.99 | AD1: Yukhoe Bibimbap | $18.99 | AE1: Injeolmi Honey Pizza | $16.99 | AF1: Lunch Box | $xx.xx | AG1: Is there anything you want to tell us? Nhà mình có tâm sự gì hong nè 😊
A2: 45733.501 | B2: huyentrang.pham@torontomu.ca | C2: Trang | D2: Pham | E2: nuts allergies | J2: Order | N2: Order | AA2: Order | AG2: draft but also my real response 😊 love u guys

Sheet TMVSA Survey Statistics
A1: Timestamp | B1: How much at most are you willing to spend? | C1: Are you okay with taking the TTC? | D1: How long are you okay with commuting? | E1: Bowling 🎳 | F1: Karaoke 🎤 | G1: Boardgame Cafe ♛ | H1: Billiards 🎱
A2: 45725.663 | B2: $30 | C2: Yes | D2: 10 | E2: 3 | F2: 4 | G2: 5 | H2: 4
A3: 45725.669 | B3: $20 | C3: Yes | D3: 10 | E3: 5 | F3: 2 | G3: 3 | H3: 4
A4: 45725.678 | B4: $20 | C4: Yes | D4: 8 | E4: 5 | F4: 2 | G4: 2 | H4: 2 | K4: Averages | L4: Std. Deviation | M4: Use filters to sort by value order.
A5: 45725.685 | B5: $30 | C5: No | D5: 10 | E5: 4 | F5: 4 | G5: 3 | H5: 3 | J5: Karaoke | K5: =AVERAGE(F:F) -> 3.952381 | L5: =STDEV(F:F) -> 1.1169687
A6: 45725.696 | B6: $30 | C6: Yes | D6: 10 | E6: 3 | F6: 4 | G6: 5 | H6: 1 | J6: Billiards | K6: =AVERAGE(H:H) -> 3.8095238 | L6: =STDEV(H:H) -> 1.0304876
A7: 45725.744 | B7: $40 | C7: Yes | D7: 6 | E7: 3 | F7: 5 | G7: 5 | H7: 5 | J7: Boardgame Cafe | K7: =AVERAGE(G:G) -> 3.8095238 | L7: =STDEV(G:G) -> 1.2891489
A8: 45725.747 | B8: $30 | C8: Yes | D8: 10 | E8: 4 | F8: 5 | G8: 1 | H8: 5 | J8: Bowling | K8: =AVERAGE(E:E) -> 3.047619 | L8: =STDEV(E:E) -> 1.16087
A9: 45725.795 | B9: $30 | C9: Yes | D9: 6 | E9: 3 | F9: 5 | G9: 5 | H9: 3
A10: 45725.874 | B10: $20 | C10: Yes | D10: 6 | E10: 2 | F10: 3 | G10: 5 | H10: 4
A11: 45725.886 | B11: $40 | C11: Yes | D11: 10 | E11: 4 | F11: 5 | G11: 5 | H11: 5
A12: 45725.892 | B12: $30 | C12: Yes | D12: 7 | E12: 3 | F12: 4 | G12: 3 | H12: 4
A13: 45725.897 | B13: $30 | C13: Yes | D13: 10 | E13: 4 | F13: 5 | G13: 3 | H13: 3
A14: 45725.975 | B14: $40 | C14: Yes | D14: 4 | E14: 2 | F14: 2 | G14: 2 | H14: 4
A15: 45726.022 | B15: $30 | C15: Yes | D15: 5 | E15: 2 | F15: 5 | G15: 3 | H15: 3
A16: 45726.616 | B16: >$50 | C16: Yes | D16: 6 | E16: 1 | F16: 3 | G16: 5 | H16: 5
A17: 45726.767 | B17: $40 | C17: Yes | D17: 10 | E17: 3 | F17: 4 | G17: 3 | H17: 4
A18: 45726.962 | B18: $30 | C18: Yes | D18: 6 | E18: 2 | F18: 5 | G18: 5 | H18: 4
A19: 45727.46 | B19: $20 | C19: Yes | D19: 7 | E19: 4 | F19: 3 | G19: 4 | H19: 5
A20: 45727.849 | B20: >$50 | C20: Yes | D20: 6 | E20: 4 | F20: 5 | G20: 5 | H20: 4
... A22: 45728.459 | B22: <$10 | C22: Yes | D22: 10 | E22: 1 | F22: 5 | G22: 5 | H22: 4
K48: 10-Point Scale Average | L48: Average (In Minutes)
J49: Commute Time Average | K49: =AVERAGE(D:D) -> 7.952381 | L49: =K49*5 -> 39.761905
K51: Average Budget | L51: Std. Deviation
J52: Budget | K52: ~ 30 | L52: -

Sheet Confirmation Results
A1: Timestamp | B1: First Name: | C1: Last Name: | D1: Email address | E1: Are you okay with spending $20-30 on dining + karaoke? Nhà mình có thể chi $20-30 cho ăn tối và karaoke hong? | F1: Will you be attending the event on March 19th? Nhà mình có tới được vào ngày 19 tháng 3 hong? | G1: Is there anything you want to tell us? Mình có điều gì muốn tâm sự hong nè 😊
A2: 45728.799 | B2: Denis | C2: Thai | D2: denis.thai@torontomu.ca | E2: Yes - Oke luôn cho sốp | F2: Yes - Đến liền! | G2: Test Response but also my real response yuhhh | I2: attend both
A3: 45728.843 | B3: Trang | C3: Pham | D3: huyentrang.pham@torontomu.ca | E3: Yes - Oke luôn cho sốp | F3: Yes - Đến liền! | G3: thank you guyssss so so much 💗 | I3: might come
A4: 45728.852 | B4: Bill | C4: Tran | D4: khuonghoang.tran@torontomu.ca | E4: Yes - Oke luôn cho sốp | F4: Yes - Đến liền! | G4: Honk | I4: nah
A5: 45728.889 | B5: Presly | C5: Trinh | D5: presly.trinh@torontomu.ca | E5: Yes - Oke luôn cho sốp | F5: Yes - Đến liền! | I5: only ehwa
A6: 45728.904 | B6: Justin | C6: Lam | D6: justin4.lam@torontomu.ca | E6: Yes - Oke luôn cho sốp | F6: Yes - Đến liền! | I6: only karaoke
A7: 45728.948 | B7: Diem | C7: Ngo | D7: diem.ngo@torontomu.ca | E7: No - Mị còn trẻ, mị cũng muốn đi chơi 😭 | F7: Yes - Đến liền! | G7: will probably only attend karaoke
A8: 45728.992 | B8: jess | C8: le | D8: j13le@torontomu.ca | E8: Yes - Oke luôn cho sốp | F8: Yes - Đến liền! | G8: iu iu iu <3 big love | J8: 15 ppl karaoke
A9: 45729.062 | B9: britney | C9: phung | D9: britney.phung@torontomu.ca | E9: Yes - Oke luôn cho sốp | F9: Yes - Đến liền! | G9: i will not be participating in the karaoke activity, i will be there for the dinner portion | J9: 14 ppl dinner (?)
A10: 45729.062 | B10: Kathy | C10: Bui | D10: k1bui@torontomu.ca | E10: Yes - Oke luôn cho sốp | F10: Yes - Đến liền! | G10: Minh không đi karaoke but i will go to the dinner! XD
A11: 45729.536 | B11: Ivy | C11: Vu | D11: my.vu@torontomu.ca | E11: No - Mị còn trẻ, mị cũng muốn đi chơi 😭 | F11: Yes - Đến liền! | G11: She might come for both ehwa and karaoke
A12: 45729.886 | B12: Hanna | C12: Phan | D12: hanna.phan@torontomu.ca | E12: Yes - Oke luôn cho sốp | F12: No - Sẽ đến bằng đường chim bay 🦅
A13: 45729.895 | B13: Khanh | C13: Su | D13: khanh.su@torontomu.ca | E13: Yes - Oke luôn cho sốp | F13: Yes - Đến liền! | G13: I will come directly to the restaurant and I will probably late.
A14: 45729.898 | B14: Bao | C14: Le | D14: ngocthienbao.le@torontomu.ca | E14: Yes - Oke luôn cho sốp | F14: Yes - Đến liền!
A15: 45729.899 | B15: Justin | C15: Nguyen | D15: justin.huy.nguyen@torontomu.ca | E15: Yes - Oke luôn cho sốp | F15: Yes - Đến liền!
A16: 45729.922 | B16: Alex | C16: Kieu | D16: alex.kieu@torontomu.ca | E16: Yes - Oke luôn cho sốp | F16: Yes - Đến liền!
A17: 45729.981 | B17: Teresa | C17: Van | D17: teresa.van@torontomu.ca | E17: Yes - Oke luôn cho sốp | F17: Yes - Đến liền! | G17: It’s 50/50 I’ll be at Karaoke but allocate a spot for me! I’ll also be commuting to dinner alone because I have a mandatory class workshop from 3-6 PM :) Good job guys
A18: 45730.048 | B18: Cherry | C18: Tran | D18: lenamphuong.tran@torontomu.ca | E18: Yes - Oke luôn cho sốp | F18: Yes - Đến liền! | G18: Mình là người ăn ngay nói thẳng, mình straight-forward á. Cho nên mình hong có vòng vo tam quốc nha, mình sẽ nói straight to the point, kiểu của mình là dzậy 🤌🏻 nhìu lúc nói đi nói lại mình cũng mệt lắm, kiểu nó tired mà nó not delivering anything á ~ nên giờ mình nói lun nè. LÀ MÌNH IU MẤY BẠN VLER 🌸 I LUV U GUYS. That's all ~ 🫶🏻🧸 EVERYONE BRINGS THEIR CAMERAAAA
A19: 45730.71 | B19: Chau | C19: Nguyen | D19: chau2.nguyen@torontomu.ca | E19: Yes - Oke luôn cho sốp | F19: No - Sẽ đến bằng đường chim bay 🦅 | G19: cứt
A20: 45730.911 | B20: Vi | C20: Phung | D20: vi.phung@torontomu.ca | E20: Yes - Oke luôn cho sốp | F20: No - Sẽ đến bằng đường chim bay 🦅
A21: 45731.933 | B21: Ryan | C21: Le | D21: sang.le@torontomu.ca | E21: Yes - Oke luôn cho sốp | F21: Yes - Đến liền!
A22: 45731.987 | B22: Chi | C22: Mai | D22: hoanguyenchi.mai@toronto.ca | E22: Yes - Oke luôn cho sốp | F22: Yes - Đến liền! | G22: i’ll join around 6:20pm and leave at 8:45pm as i’ll have another plan ^^
A23: 45732.431 | B23: sodana | C23: ung | D23: sodana.ung@torontomu.ca | E23: No - Mị còn trẻ, mị cũng muốn đi chơi 😭 | F23: No - Sẽ đến bằng đường chim bay 🦅

Sheet Links
A1: Presentation: | B1: https://docs.google.com/presentation/d/11bqyeZxr0WC58j-DEv2aVUN9QBZhJ4DIwzCbjay6eGI/edit?usp=sharing | C1: Editor Links
A2: Form: | B2: https://forms.gle/K4xRtPzM5oP1gYtYA | C2: Form | D2: https://docs.google.com/forms/d/1PHfR4JBCMjRXVgaLJdNX_0jMnOGJzL_H4g6Dcy6Rnq4/edit
A3: Order Form (Ehwa): | B3: https://forms.gle/wMa2jRDPtt6fZPHk6 | C3: Order Form (Ehwa): | D3: https://docs.google.com/forms/d/1h_KZ8B-ozkQ4X4b96x8HLLxx2-ODGD2Kb4URK4qAdQU/edit
A4: Confirmation Form | B4: https://forms.gle/7xcReJ1jcaNzcG1G9 | C4: Confirmation Form | D4: https://docs.google.com/forms/d/16Cx4vI8zIWzfiaflsk4MEH5NgzPlxNjd42qLeH28T5s/edit
